vcd_dft/__init__.py
vcd_dft/vcd_regions_plotter.py
vcd_dft-0.2.0.dist-info/WHEEL
vcd_dft-0.2.0.dist-info/entry_points.txt
vcd_dft-0.2.0.dist-info/METADATA
vcd_dft-0.2.0.dist-info/RECORD
