Metadata-Version: 2.3
Name: vcd-dft
Version: 0.2.0
Summary: Add your description here
Author: Haden Cavalli
Author-email: Haden Cavalli <hadencavalli@gmail.com>
Requires-Dist: matplotlib>=3.10.7
Requires-Dist: numpy>=2.3.5
Requires-Python: >=3.13
